{"price": 46.27, "change": 0.1, "changePct": 0.22, "time": "2026-04-06 11:00", "ma5": 47.57, "ma10": 48.06, "ma20": 52.9, "ma60": 48.82, "rsi": 38.83, "dif": -2.09, "dea": -1.079, "bar": -2.023, "barConverging": true, "barHistory": [-4.987, -4.684, -4.31, -4.188, -3.717, -3.211, -2.869, -2.351, -2.239, -2.023], "barDates": ["03-23", "03-24", "03-25", "03-26", "03-27", "03-30", "03-31", "04-01", "04-02", "04-03"], "bollUpper": 65.53, "bollMid": 52.9, "bollLower": 40.28, "K": 17.5, "D": 18.96, "J": 14.57, "rsiBearDivergence": false, "volRatio": 0.74, "signal": 1, "ma_trend": "空头"}