{"price": 58.18, "change": -0.36, "changePct": -0.61, "time": "2026-04-21 10:03", "ma5": 54.4, "ma10": 51.78, "ma20": 49.92, "ma60": 52.3, "rsi": 63.27, "dif": 0.674, "dea": -0.686, "bar": 2.72, "barConverging": false, "barHistory": [-0.856, -0.444, -0.154, -0.014, 0.308, 0.171, 0.708, 1.574, 2.367, 2.72], "barDates": ["04-08", "04-09", "04-10", "04-13", "04-14", "04-15", "04-16", "04-17", "04-20", "04-21"], "bollUpper": 56.95, "bollMid": 49.92, "bollLower": 42.89, "K": 81.42, "D": 74.77, "J": 94.7, "rsiBearDivergence": false, "volRatio": 0.25, "signal": 1, "ma_trend": "多头"}