{"price": 77.05, "change": -0.75, "changePct": -0.96, "time": "2026-04-21 14:01", "ma5": 73.61, "ma10": 69.4, "ma20": 65.97, "ma60": 71.71, "rsi": 66.29, "dif": 1.766, "dea": -0.245, "bar": 4.022, "barConverging": false, "barHistory": [1.191, 1.305, 1.364, 1.32, 1.91, 2.211, 2.485, 3.209, 3.886, 4.022], "barDates": ["04-08", "04-09", "04-10", "04-13", "04-14", "04-15", "04-16", "04-17", "04-20", "04-21"], "bollUpper": 76.23, "bollMid": 65.97, "bollLower": 55.7, "K": 83.59, "D": 76.12, "J": 98.52, "rsiBearDivergence": false, "volRatio": 0.81, "signal": 0, "ma_trend": "多头"}