{"price": 136.61, "change": -2.85, "changePct": -2.04, "time": "2026-04-15 10:02", "ma5": 132.98, "ma10": 129.92, "ma20": 147.1, "ma60": 153.58, "rsi": 42.68, "dif": -7.394, "dea": -6.605, "bar": -1.577, "barConverging": true, "barHistory": [-6.361, -8.831, -10.431, -11.008, -10.156, -9.438, -7.52, -5.385, -2.989, -1.577], "barDates": ["04-01", "04-02", "04-03", "04-07", "04-08", "04-09", "04-10", "04-13", "04-14", "04-15"], "bollUpper": 183.41, "bollMid": 147.1, "bollLower": 110.79, "K": 51.31, "D": 31.89, "J": 90.13, "rsiBearDivergence": false, "volRatio": 0.48, "signal": 2, "ma_trend": "混排"}