{"price": 135.73, "change": 0.53, "changePct": 0.39, "time": "2026-04-21 14:30", "ma5": 134.29, "ma10": 132.68, "ma20": 140.15, "ma60": 151.45, "rsi": 42.95, "dif": -6.18, "dea": -6.75, "bar": 1.139, "barConverging": false, "barHistory": [-10.035, -9.325, -7.415, -5.288, -2.898, -1.84, -0.956, -0.372, 0.453, 1.139], "barDates": ["04-08", "04-09", "04-10", "04-13", "04-14", "04-15", "04-16", "04-17", "04-20", "04-21"], "bollUpper": 170.07, "bollMid": 140.15, "bollLower": 110.23, "K": 59.72, "D": 51.15, "J": 76.86, "rsiBearDivergence": false, "volRatio": 0.69, "signal": 1, "ma_trend": "混排"}