{"price": 134.41, "change": -2.5, "changePct": -1.83, "time": "2026-04-23 14:31", "ma5": 135.1, "ma10": 134.78, "ma20": 137.15, "ma60": 150.38, "rsi": 42.13, "dif": -5.246, "dea": -6.167, "bar": 1.843, "barConverging": false, "barHistory": [-7.547, -5.411, -3.013, -1.947, -1.054, -0.464, 0.368, 1.124, 1.747, 1.843], "barDates": ["04-10", "04-13", "04-14", "04-15", "04-16", "04-17", "04-20", "04-21", "04-22", "04-23"], "bollUpper": 161.68, "bollMid": 137.15, "bollLower": 112.63, "K": 55.85, "D": 55.53, "J": 56.5, "rsiBearDivergence": false, "volRatio": 1.0, "signal": 0, "ma_trend": "混排"}