{"price": 130.33, "change": 6.53, "changePct": 5.27, "time": "2026-04-10 13:00", "ma5": 125.34, "ma10": 135.96, "ma20": 152.3, "ma60": 155.12, "rsi": 35.85, "dif": -9.267, "dea": -5.528, "bar": -7.478, "barConverging": true, "barHistory": [-0.29, -1.628, -3.24, -6.206, -8.686, -10.296, -10.883, -10.04, -9.33, -7.478], "barDates": ["03-27", "03-30", "03-31", "04-01", "04-02", "04-03", "04-07", "04-08", "04-09", "04-10"], "bollUpper": 191.23, "bollMid": 152.3, "bollLower": 113.37, "K": 10.8, "D": 9.93, "J": 12.55, "rsiBearDivergence": false, "volRatio": 1.15, "signal": 1, "ma_trend": "空头"}