{"price": 92.81, "change": 2.76, "changePct": 3.06, "time": "2026-04-22 14:31", "ma5": 93.62, "ma10": 91.31, "ma20": 87.21, "ma60": 86.49, "rsi": 56.66, "dif": 1.998, "dea": 1.206, "bar": 1.585, "barConverging": true, "barHistory": [-0.002, 0.45, 1.001, 1.549, 1.706, 2.423, 2.553, 2.608, 1.834, 1.585], "barDates": ["04-09", "04-10", "04-13", "04-14", "04-15", "04-16", "04-17", "04-20", "04-21", "04-22"], "bollUpper": 97.13, "bollMid": 87.21, "bollLower": 77.29, "K": 64.32, "D": 69.83, "J": 53.31, "rsiBearDivergence": false, "volRatio": 0.82, "signal": 1, "ma_trend": "多头"}