{"price": 92.05, "change": -0.9, "changePct": -0.97, "time": "2026-04-27 09:31", "ma5": 92.88, "ma10": 93.11, "ma20": 88.52, "ma60": 86.95, "rsi": 53.29, "dif": 1.956, "dea": 1.448, "bar": 1.015, "barConverging": true, "barHistory": [1.873, 2.007, 2.703, 2.812, 2.849, 2.058, 1.883, 1.961, 1.514, 1.015], "barDates": ["04-14", "04-15", "04-16", "04-17", "04-20", "04-21", "04-22", "04-23", "04-24", "04-27"], "bollUpper": 99.24, "bollMid": 88.52, "bollLower": 77.8, "K": 47.66, "D": 59.81, "J": 23.35, "rsiBearDivergence": false, "volRatio": 0.03, "signal": 2, "ma_trend": "混排"}