{"price": 95.66, "change": 2.16, "changePct": 2.31, "time": "2026-04-23 14:00", "ma5": 93.74, "ma10": 92.21, "ma20": 87.65, "ma60": 86.71, "rsi": 59.43, "dif": 2.179, "dea": 1.251, "bar": 1.858, "barConverging": false, "barHistory": [0.676, 1.211, 1.745, 1.888, 2.592, 2.709, 2.753, 1.969, 1.801, 1.858], "barDates": ["04-10", "04-13", "04-14", "04-15", "04-16", "04-17", "04-20", "04-21", "04-22", "04-23"], "bollUpper": 98.31, "bollMid": 87.65, "bollLower": 76.99, "K": 68.35, "D": 69.74, "J": 65.57, "rsiBearDivergence": false, "volRatio": 1.08, "signal": 0, "ma_trend": "多头"}