{"price": 93.95, "change": -0.34, "changePct": -0.36, "time": "2026-04-20 14:00", "ma5": 93.08, "ma10": 89.54, "ma20": 86.49, "ma60": 85.57, "rsi": 60.45, "dif": 2.075, "dea": 0.893, "bar": 2.364, "barConverging": true, "barHistory": [-1.95, -0.904, -0.144, 0.318, 0.878, 1.435, 1.6, 2.325, 2.461, 2.364], "barDates": ["04-07", "04-08", "04-09", "04-10", "04-13", "04-14", "04-15", "04-16", "04-17", "04-20"], "bollUpper": 95.83, "bollMid": 86.49, "bollLower": 77.16, "K": 77.48, "D": 74.71, "J": 83.03, "rsiBearDivergence": false, "volRatio": 0.76, "signal": 1, "ma_trend": "多头"}