{"price": 27.43, "change": -0.79, "changePct": -2.8, "time": "2026-04-16 10:32", "ma5": 27.43, "ma10": 26.78, "ma20": 27.37, "ma60": 28.74, "rsi": 47.59, "dif": -0.496, "dea": -0.654, "bar": 0.317, "barConverging": false, "barHistory": [-0.724, -0.791, -0.801, -0.554, -0.383, -0.196, -0.078, 0.086, 0.292, 0.317], "barDates": ["04-02", "04-03", "04-07", "04-08", "04-09", "04-10", "04-13", "04-14", "04-15", "04-16"], "bollUpper": 29.34, "bollMid": 27.37, "bollLower": 25.39, "K": 70.8, "D": 59.32, "J": 93.77, "rsiBearDivergence": false, "volRatio": 0.7, "signal": 0, "ma_trend": "混排"}