{"price": 39.94, "change": -0.41, "changePct": -1.02, "time": "2026-04-28 11:01", "ma5": 41.56, "ma10": 41.43, "ma20": 39.57, "ma60": 36.05, "rsi": 51.65, "dif": 1.229, "dea": 1.299, "bar": -0.141, "barConverging": true, "barHistory": [0.053, 0.465, 0.644, 0.808, 0.788, 0.741, 0.858, 0.564, 0.183, -0.141], "barDates": ["04-15", "04-16", "04-17", "04-20", "04-21", "04-22", "04-23", "04-24", "04-27", "04-28"], "bollUpper": 44.41, "bollMid": 39.57, "bollLower": 34.73, "K": 44.67, "D": 62.85, "J": 8.32, "rsiBearDivergence": false, "volRatio": 0.35, "signal": 2, "ma_trend": "多头"}