{"price": 150.7, "change": -0.3, "changePct": -0.2, "time": "2026-04-17 14:31", "ma5": 150.91, "ma10": 143.16, "ma20": 139.06, "ma60": 152.93, "rsi": 56.59, "dif": 0.393, "dea": -2.386, "bar": 5.558, "barConverging": true, "barHistory": [-2.726, -2.205, -0.204, 1.17, 2.639, 4.647, 5.893, 5.658, 5.771, 5.558], "barDates": ["04-03", "04-07", "04-08", "04-09", "04-10", "04-13", "04-14", "04-15", "04-16", "04-17"], "bollUpper": 156.39, "bollMid": 139.06, "bollLower": 121.73, "K": 71.63, "D": 68.91, "J": 77.08, "rsiBearDivergence": false, "volRatio": 0.83, "signal": 1, "ma_trend": "多头"}