{"price": 144.81, "change": -2.37, "changePct": -1.61, "time": "2026-04-16 09:31", "ma5": 148.24, "ma10": 140.37, "ma20": 138.7, "ma60": 152.53, "rsi": 51.84, "dif": -0.66, "dea": -3.137, "bar": 4.955, "barConverging": true, "barHistory": [-3.077, -2.774, -2.25, -0.246, 1.131, 2.603, 4.613, 5.862, 5.629, 4.955], "barDates": ["04-02", "04-03", "04-07", "04-08", "04-09", "04-10", "04-13", "04-14", "04-15", "04-16"], "bollUpper": 155.23, "bollMid": 138.7, "bollLower": 122.17, "K": 65.59, "D": 65.47, "J": 65.83, "rsiBearDivergence": false, "volRatio": 0.03, "signal": 2, "ma_trend": "多头"}