{"price": 150.67, "change": 7.14, "changePct": 4.97, "time": "2026-04-13 11:30", "ma5": 140.1, "ma10": 134.4, "ma20": 138.99, "ma60": 151.64, "rsi": 57.96, "dif": -3.046, "dea": -5.263, "bar": 4.433, "barConverging": false, "barHistory": [-3.112, -3.866, -3.449, -3.034, -2.735, -2.213, -0.212, 1.163, 2.633, 4.433], "barDates": ["03-30", "03-31", "04-01", "04-02", "04-03", "04-07", "04-08", "04-09", "04-10", "04-13"], "bollUpper": 156.16, "bollMid": 138.99, "bollLower": 121.82, "K": 73.04, "D": 54.75, "J": 109.61, "rsiBearDivergence": false, "volRatio": 1.09, "signal": 0, "ma_trend": "混排"}