{"price": 173.14, "change": -4.95, "changePct": -2.78, "time": "2026-04-28 12:01", "ma5": 167.56, "ma10": 159.98, "ma20": 148.34, "ma60": 154.65, "rsi": 66.23, "dif": 6.552, "dea": 2.888, "bar": 7.328, "barConverging": true, "barHistory": [6.011, 6.099, 5.873, 5.97, 6.234, 6.729, 6.23, 6.071, 7.496, 7.328], "barDates": ["04-15", "04-16", "04-17", "04-20", "04-21", "04-22", "04-23", "04-24", "04-27", "04-28"], "bollUpper": 178.59, "bollMid": 148.34, "bollLower": 118.08, "K": 80.83, "D": 79.51, "J": 83.48, "rsiBearDivergence": false, "volRatio": 0.73, "signal": 1, "ma_trend": "多头"}