[
  {
    "code": "300274",
    "market": "sz",
    "name": "阳光电源",
    "sector": "光伏/储能",
    "price": 136.72,
    "change": 0.49,
    "changePct": 0.36,
    "signal": 0,
    "signalMax": 5,
    "rsi": 43.93,
    "ma_trend": "混排",
    "ma5": 134.96,
    "ma20": 138.78,
    "J": 78.0,
    "time": "2026-04-22 14:31"
  },
  {
    "code": "688008",
    "market": "sh",
    "name": "澜起科技",
    "sector": "半导体",
    "price": 163.51,
    "change": 5.11,
    "changePct": 3.23,
    "signal": 0,
    "signalMax": 5,
    "rsi": 65.65,
    "ma_trend": "多头",
    "ma5": 155.67,
    "ma20": 141.93,
    "J": 101.99,
    "time": "2026-04-22 14:31"
  },
  {
    "code": "300442",
    "market": "sz",
    "name": "润泽科技",
    "sector": "IDC/算力",
    "price": 92.78,
    "change": 2.73,
    "changePct": 3.03,
    "signal": 1,
    "signalMax": 5,
    "rsi": 56.64,
    "ma_trend": "多头",
    "ma5": 93.62,
    "ma20": 87.21,
    "J": 53.25,
    "time": "2026-04-22 14:31"
  },
  {
    "code": "600089",
    "market": "sh",
    "name": "特变电工",
    "sector": "特高压",
    "price": 27.44,
    "change": -0.11,
    "changePct": -0.4,
    "signal": 2,
    "signalMax": 5,
    "rsi": 46.91,
    "ma_trend": "多头",
    "ma5": 27.63,
    "ma20": 27.26,
    "J": 52.59,
    "time": "2026-04-22 14:31"
  },
  {
    "code": "600875",
    "market": "sh",
    "name": "东方电气",
    "sector": "电力装备",
    "price": 42.1,
    "change": 0.09,
    "changePct": 0.21,
    "signal": 1,
    "signalMax": 5,
    "rsi": 61.22,
    "ma_trend": "多头",
    "ma5": 42.08,
    "ma20": 38.61,
    "J": 88.74,
    "time": "2026-04-22 14:31"
  },
  {
    "code": "300136",
    "market": "sz",
    "name": "信维通信",
    "sector": "消费电子",
    "price": 79.79,
    "change": 2.75,
    "changePct": 3.57,
    "signal": 0,
    "signalMax": 5,
    "rsi": 69.41,
    "ma_trend": "多头",
    "ma5": 75.87,
    "ma20": 66.97,
    "J": 105.36,
    "time": "2026-04-22 14:31"
  },
  {
    "code": "000657",
    "market": "sz",
    "name": "中钨高新",
    "sector": "钨材料",
    "price": 58.01,
    "change": 0.2,
    "changePct": 0.35,
    "signal": 1,
    "signalMax": 5,
    "rsi": 62.42,
    "ma_trend": "多头",
    "ma5": 56.48,
    "ma20": 50.31,
    "J": 89.61,
    "time": "2026-04-22 14:31"
  }
]