[
  {
    "code": "300274",
    "market": "sz",
    "name": "阳光电源",
    "sector": "光伏/储能",
    "price": 124.23,
    "change": 0.91,
    "changePct": 0.74,
    "signal": 2,
    "signalMax": 5,
    "rsi": 26.29,
    "ma_trend": "空头",
    "ma5": 132.0,
    "ma20": 158.35,
    "J": -7.87,
    "time": "2026-04-07 09:47"
  },
  {
    "code": "688008",
    "market": "sh",
    "name": "澜起科技",
    "sector": "半导体",
    "price": 130.18,
    "change": 2.92,
    "changePct": 2.29,
    "signal": 2,
    "signalMax": 5,
    "rsi": 39.54,
    "ma_trend": "空头",
    "ma5": 128.34,
    "ma20": 140.33,
    "J": 21.75,
    "time": "2026-04-07 09:47"
  },
  {
    "code": "300442",
    "market": "sz",
    "name": "润泽科技",
    "sector": "IDC/算力",
    "price": 81.44,
    "change": 0.44,
    "changePct": 0.54,
    "signal": 2,
    "signalMax": 5,
    "rsi": 45.94,
    "ma_trend": "空头",
    "ma5": 81.62,
    "ma20": 85.1,
    "J": 9.77,
    "time": "2026-04-07 09:47"
  },
  {
    "code": "600089",
    "market": "sh",
    "name": "特变电工",
    "sector": "特高压",
    "price": 25.62,
    "change": 0.12,
    "changePct": 0.47,
    "signal": 2,
    "signalMax": 5,
    "rsi": 34.39,
    "ma_trend": "空头",
    "ma5": 26.11,
    "ma20": 28.39,
    "J": 1.21,
    "time": "2026-04-07 09:47"
  },
  {
    "code": "600875",
    "market": "sh",
    "name": "东方电气",
    "sector": "电力装备",
    "price": 36.18,
    "change": -0.68,
    "changePct": -1.84,
    "signal": 2,
    "signalMax": 5,
    "rsi": 49.24,
    "ma_trend": "混排",
    "ma5": 36.74,
    "ma20": 37.84,
    "J": 41.81,
    "time": "2026-04-07 09:47"
  },
  {
    "code": "300136",
    "market": "sz",
    "name": "信维通信",
    "sector": "消费电子",
    "price": 61.7,
    "change": -0.07,
    "changePct": -0.11,
    "signal": 2,
    "signalMax": 5,
    "rsi": 41.85,
    "ma_trend": "空头",
    "ma5": 62.6,
    "ma20": 63.82,
    "J": 16.26,
    "time": "2026-04-07 09:47"
  },
  {
    "code": "000657",
    "market": "sz",
    "name": "中钨高新",
    "sector": "钨材料",
    "price": 47.92,
    "change": 1.65,
    "changePct": 3.57,
    "signal": 2,
    "signalMax": 5,
    "rsi": 43.03,
    "ma_trend": "空头",
    "ma5": 47.39,
    "ma20": 52.04,
    "J": 31.53,
    "time": "2026-04-07 09:47"
  }
]