[
  {
    "code": "300274",
    "market": "sz",
    "name": "阳光电源",
    "sector": "光伏/储能",
    "price": 126.6,
    "change": 4.32,
    "changePct": 3.53,
    "signal": 2,
    "signalMax": 5,
    "rsi": 29.87,
    "ma_trend": "空头",
    "ma5": 126.78,
    "ma20": 156.78,
    "J": -1.82,
    "time": "2026-04-08 12:00"
  },
  {
    "code": "688008",
    "market": "sh",
    "name": "澜起科技",
    "sector": "半导体",
    "price": 136.44,
    "change": 8.54,
    "changePct": 6.68,
    "signal": 1,
    "signalMax": 5,
    "rsi": 45.94,
    "ma_trend": "空头",
    "ma5": 130.11,
    "ma20": 139.39,
    "J": 59.49,
    "time": "2026-04-08 12:00"
  },
  {
    "code": "300442",
    "market": "sz",
    "name": "润泽科技",
    "sector": "IDC/算力",
    "price": 85.95,
    "change": 6.44,
    "changePct": 8.1,
    "signal": 1,
    "signalMax": 5,
    "rsi": 52.56,
    "ma_trend": "空头",
    "ma5": 82.25,
    "ma20": 84.52,
    "J": 58.84,
    "time": "2026-04-08 12:00"
  },
  {
    "code": "600089",
    "market": "sh",
    "name": "特变电工",
    "sector": "特高压",
    "price": 26.77,
    "change": 1.42,
    "changePct": 5.6,
    "signal": 1,
    "signalMax": 5,
    "rsi": 43.21,
    "ma_trend": "空头",
    "ma5": 26.11,
    "ma20": 28.12,
    "J": 26.13,
    "time": "2026-04-08 12:00"
  },
  {
    "code": "600875",
    "market": "sh",
    "name": "东方电气",
    "sector": "电力装备",
    "price": 38.02,
    "change": 3.2,
    "changePct": 9.19,
    "signal": 1,
    "signalMax": 5,
    "rsi": 54.17,
    "ma_trend": "混排",
    "ma5": 37.06,
    "ma20": 37.57,
    "J": 66.92,
    "time": "2026-04-08 12:00"
  },
  {
    "code": "300136",
    "market": "sz",
    "name": "信维通信",
    "sector": "消费电子",
    "price": 64.99,
    "change": 4.31,
    "changePct": 7.1,
    "signal": 0,
    "signalMax": 5,
    "rsi": 49.12,
    "ma_trend": "空头",
    "ma5": 62.4,
    "ma20": 63.51,
    "J": 37.12,
    "time": "2026-04-08 12:00"
  },
  {
    "code": "000657",
    "market": "sz",
    "name": "中钨高新",
    "sector": "钨材料",
    "price": 49.22,
    "change": 1.58,
    "changePct": 3.32,
    "signal": 1,
    "signalMax": 5,
    "rsi": 46.23,
    "ma_trend": "空头",
    "ma5": 47.63,
    "ma20": 51.17,
    "J": 69.66,
    "time": "2026-04-08 12:00"
  }
]